[{"id":"otdb_677a86f2255e","question":"What country did Shirley Bassey originate from?","correct_answer":"Wales","incorrect_answers":["America","England","Canada"],"category":"Entertainment: Music","difficulty":"medium"},{"id":"otdb_7e9e72492836","question":"EDM producer Marshmello performs live wearing clothes and a marshmallow mask of what colour?","correct_answer":"White","incorrect_answers":["Black","Blue","Yellow"],"category":"Entertainment: Music","difficulty":"medium"},{"id":"otdb_6b84c17f2eb3","question":"Long John Baldry, the voice of Dr. Robotnik in Adventures Of Sonic The Hedgehog, was in a band with which music artist in the 1960s?","correct_answer":"Elton John","incorrect_answers":["Freddie Mercury","Paul McCartney","Johnny Cash"],"category":"Entertainment: Music","difficulty":"hard"},{"id":"otdb_d596fe1df165","question":"Which of these is NOT a song by Pegboard Nerds?","correct_answer":"WiFi Tears","incorrect_answers":["Swamp Thing","Emoji","BAMF"],"category":"Entertainment: Music","difficulty":"medium"},{"id":"otdb_81620c8b0ad5","question":"What is the opening track on Lorde's Pure Heroine?","correct_answer":"Tennis Court","incorrect_answers":["Team","Royals","400 Lux"],"category":"Entertainment: Music","difficulty":"medium"},{"id":"otdb_c7b93a1c2346","question":"Which of the following guitarists recorded an album as a member of the Red Hot Chili Peppers?","correct_answer":"Dave Navarro","incorrect_answers":["Tom Morello ","Billy Corgan","Ed O'Brien"],"category":"Entertainment: Music","difficulty":"medium"},{"id":"otdb_ea97eb6d4551","question":"Rick Astley's hit song \"Never Gonna Give You Up\" was released in what year?","correct_answer":"1987","incorrect_answers":["1985","1986","1988"],"category":"Entertainment: Music","difficulty":"medium"},{"id":"otdb_5753eb329f50","question":"Who is the lead singer of Arctic Monkeys?","correct_answer":"Alex Turner","incorrect_answers":["Jamie Cook","Matt Helders","Nick O'Malley"],"category":"Entertainment: Music","difficulty":"easy"},{"id":"otdb_2360e8b37ca4","question":"According to the RIAA: Which artist has sold the most albums by the million?","correct_answer":"The Beatles","incorrect_answers":["Elvis Presley","Michael Jackson","Pink Floyd"],"category":"Entertainment: Music","difficulty":"medium"},{"id":"otdb_091ede05ece6","question":"Who is the frontman of Muse?","correct_answer":"Matt Bellamy","incorrect_answers":["Dominic Howard","Thom Yorke","Jonny Greenwood"],"category":"Entertainment: Music","difficulty":"medium"},{"id":"otdb_d1ebbd13a27c","question":"Which of these is NOT the name of an album released by English singer-songwriter Adele?","correct_answer":"12","incorrect_answers":["19","21","25"],"category":"Entertainment: Music","difficulty":"easy"},{"id":"otdb_de8012fba1c3","question":"Which Twitch streamer is the vocalist for Red Vox?","correct_answer":"Vinesauce","incorrect_answers":["The8BitDrummer","LIRIK","Sodapoppin"],"category":"Entertainment: Music","difficulty":"easy"},{"id":"otdb_9239839e47bd","question":"Which of the following is NOT a real song from the band Thousand Foot Krutch?","correct_answer":"Limitless Fury","incorrect_answers":["Let The Sparks Fly","Down","Give Up The Ghost"],"category":"Entertainment: Music","difficulty":"hard"},{"id":"otdb_4c4a65cbdf12","question":"Which of these is NOT a song on The Beatles' 1968 self titled album, also known as the White album?","correct_answer":"Being For The Benefit Of Mr. Kite!","incorrect_answers":["Why Don't We Do It in the Road?","Everybody's Got Something to Hide Except Me and My Monkey","The Continuing Story of Bungalow Bill"],"category":"Entertainment: Music","difficulty":"medium"},{"id":"otdb_cd0d4501edc1","question":"Which song is NOT by singer Tom Jones?","correct_answer":"Never Gonna Give You Up","incorrect_answers":["It's Not Unusual","What's New Pussycat","Delilah"],"category":"Entertainment: Music","difficulty":"easy"},{"id":"otdb_06898e973a9c","question":"Which famous rapper is featured in Jack &Uuml; (Skrillex and Diplo)'s 2015 single called \"Febreze\"?","correct_answer":"2 Chainz","incorrect_answers":["Kendrick Lamar","Future","Fatman Scoop"],"category":"Entertainment: Music","difficulty":"easy"},{"id":"otdb_a60b34728e50","question":"Which artist released the 2012 single \"Harlem Shake\", which was used in numerous YouTube videos in 2013?","correct_answer":"Baauer","incorrect_answers":["RL Grime","NGHTMRE","Flosstradamus"],"category":"Entertainment: Music","difficulty":"easy"},{"id":"otdb_e0a77eedd85a","question":"Which of the following music bands is not from Finland?","correct_answer":"Sabaton","incorrect_answers":["Apocalyptica","Waltari","Lordi"],"category":"Entertainment: Music","difficulty":"medium"},{"id":"otdb_ca24be99c113","question":"Who is the primary lyricist for Canadian progressive rock band Rush?","correct_answer":"Neil Peart","incorrect_answers":["Geddy Lee","Alex Lifeson","John Rutsey"],"category":"Entertainment: Music","difficulty":"medium"},{"id":"otdb_f91674bb2293","question":"\"Some people call me the space cowboy\" is the first line from what song?","correct_answer":"The Joker","incorrect_answers":["Fandango","Take The Money and Run","Fly Like an Eagle"],"category":"Entertainment: Music","difficulty":"easy"},{"id":"otdb_662f0389a5f6","question":"EDM record label Monstercat is based in which country?","correct_answer":"Canada","incorrect_answers":["United States","Australia","United Kingdom"],"category":"Entertainment: Music","difficulty":"medium"},{"id":"otdb_a7b27075b3cb","question":"Which band released the album \"Sonic Highways\" in 2014?","correct_answer":"Foo Fighters","incorrect_answers":["Coldplay","Nickelback","The Flaming Lips"],"category":"Entertainment: Music","difficulty":"medium"},{"id":"otdb_c83f533df0d8","question":"Which of these is NOT the name of an album released by American rapper Viper?","correct_answer":"The Life of Pablo","incorrect_answers":["Kill Urself My Man","You'll Cowards Don't Even Smoke Crack","Yo Wife Handcuffin' Me"],"category":"Entertainment: Music","difficulty":"medium"},{"id":"otdb_49607e3b7db3","question":"\"Doctor Jones\", \"Turn Back Time\" and \"Barbie Girl\" were UK number ones for which Eurodance group?","correct_answer":"Aqua","incorrect_answers":["Vengaboys","Eiffel 65","Sash!"],"category":"Entertainment: Music","difficulty":"easy"},{"id":"otdb_e3e5e88af891","question":"The 2023 Beatles song \"Now and Then\" originated from an unfinished demo recorded by which Beatle?","correct_answer":"John Lennon","incorrect_answers":["Paul McCartney","George Harrison","Ringo Starr"],"category":"Entertainment: Music","difficulty":"medium"},{"id":"otdb_5c0b0f201e86","question":"Who is the lead singer of the Smashing Pumpkins?","correct_answer":"Billy Corgan","incorrect_answers":["Brett Scallions","Eddie Vedder","Chino Moreno"],"category":"Entertainment: Music","difficulty":"medium"},{"id":"otdb_20d4c4f5ca05","question":"Which band is the longest active band in the world with no breaks or line-up changes?","correct_answer":"U2","incorrect_answers":["Radiohead","Rush","Rolling Stones"],"category":"Entertainment: Music","difficulty":"hard"},{"id":"otdb_9bec4baf9996","question":"What is the name of the album released in 2014 by American band Maroon 5?","correct_answer":"V","incorrect_answers":["X","III","IV"],"category":"Entertainment: Music","difficulty":"easy"},{"id":"otdb_a114ab064166","question":"Which European capital city gives its name to a 1981 song by Ultravox?","correct_answer":"Vienna","incorrect_answers":["Berlin","Paris","Brussels"],"category":"Entertainment: Music","difficulty":"medium"},{"id":"otdb_5a6c285ff700","question":"When did The Beatles release the LP \"Please Please Me\"?","correct_answer":"1963","incorrect_answers":["1970","1960","1969"],"category":"Entertainment: Music","difficulty":"medium"},{"id":"otdb_4b5fd9debed4","question":"Which member of the British pop group \"The Spice Girls\" was known as Ginger Spice?","correct_answer":"Geri Halliwell","incorrect_answers":["Melanie Brown","Emma Bunton","Victoria Beckham"],"category":"Entertainment: Music","difficulty":"medium"},{"id":"otdb_04880d73ca80","question":"From which album is the Gorillaz song, \"On Melancholy Hill\" featured in?","correct_answer":"Plastic Beach","incorrect_answers":["Demon Days","Humanz","The Fall"],"category":"Entertainment: Music","difficulty":"medium"},{"id":"otdb_7a55845bfef2","question":"The letters in the name of the band \"TWRP\" stand for what?","correct_answer":"Tupperware Remix Party","incorrect_answers":["Totally Wicked Robot Performers","Team Wild and the Radio Pirates","Taiwan Roleplay"],"category":"Entertainment: Music","difficulty":"medium"},{"id":"otdb_71b4361b4946","question":"Where does the Mac part of the name Fleetwood Mac come from?","correct_answer":"John McVie","incorrect_answers":["Christine McVie","Mac McAnally","David Tennant"],"category":"Entertainment: Music","difficulty":"easy"},{"id":"otdb_70c35b8cb87a","question":"Who had a 1969 top 5 hit with the song,  'A Boy Named Sue'?","correct_answer":"Johnny Cash","incorrect_answers":["Bob Dylan","Willie Nelson","Kris Kristofferson"],"category":"Entertainment: Music","difficulty":"easy"},{"id":"otdb_2368400f5f98","question":"Kanye West's \"Gold Digger\" featured which Oscar-winning actor?","correct_answer":"Jamie Foxx","incorrect_answers":["Alec Baldwin","Dwayne Johnson"," Bruce Willis"],"category":"Entertainment: Music","difficulty":"easy"},{"id":"otdb_26cf86d27e26","question":"Which of these artists do NOT originate from France?","correct_answer":"The Chemical Brothers","incorrect_answers":["Air","Justice","Daft Punk"],"category":"Entertainment: Music","difficulty":"medium"},{"id":"otdb_bd81df999c19","question":"Which M83 album is the song \"Midnight City\" featured in?","correct_answer":"Hurry Up, We're Dreaming","incorrect_answers":["Saturdays = Youth","Before the Dawn Heals Us","Junk"],"category":"Entertainment: Music","difficulty":"hard"},{"id":"otdb_e3fd3de7373b","question":"What song originally performed by The Bee Gees in 1978 had a cover version by Steps 20 years later?","correct_answer":"Tragedy","incorrect_answers":["Night Fever","Stayin' Alive","You Should Be Dancing"],"category":"Entertainment: Music","difficulty":"hard"},{"id":"otdb_db196f19bfcb","question":"Which of Michael Jackson's albums sold the most copies?","correct_answer":"Thriller","incorrect_answers":["Dangerous","Bad","Off the Wall"],"category":"Entertainment: Music","difficulty":"hard"},{"id":"otdb_3628077ff3b9","question":"Which of these artists has NOT been a member of dancehall group Major Lazer?","correct_answer":"Skrillex","incorrect_answers":["Diplo","Jillionaire","Walshy Fire"],"category":"Entertainment: Music","difficulty":"medium"},{"id":"otdb_a96bd0a65769","question":"Which of these is not an Ed Sheeran album?","correct_answer":"-","incorrect_answers":["+","X","&divide;"],"category":"Entertainment: Music","difficulty":"medium"},{"id":"otdb_b14d7dc14541","question":"Which of these songs is NOT included in the Suicide Squad OST?","correct_answer":"Skies on Fire - AC/DC","incorrect_answers":["Heathens - Twenty One Pilots","Without Me - Eminem","Fortunate Son - Creedence Clearwater Revival"],"category":"Entertainment: Music","difficulty":"hard"},{"id":"otdb_d6e488b90553","question":"Which of these bands was a featuring artist in Compton rapper Kendrick Lamar's 2017 album, \"DAMN.\"?","correct_answer":"U2","incorrect_answers":["Radiohead","Coldplay","Bon Jovi"],"category":"Entertainment: Music","difficulty":"medium"},{"id":"otdb_09afd35efd0d","question":"Which of these languages was NOT included in the 2016 song \"Don't Mind\" by Kent Jones?","correct_answer":"Portuguese","incorrect_answers":["Japanese","French","Spanish"],"category":"Entertainment: Music","difficulty":"medium"},{"id":"otdb_7c8e421e72b5","question":"Which Elton John hit starts with the line \"When are you gonna come down\"?","correct_answer":"Goodbye Yellow Brick Road","incorrect_answers":["Rocket Man","Bennie and the Jets","Crocodile Rock"],"category":"Entertainment: Music","difficulty":"hard"},{"id":"otdb_0e4c1e34c186","question":"Which band had hits in 1975 with the songs, 'One Of These Nights' & 'Lyin Eyes'?","correct_answer":"The Eagles","incorrect_answers":["Fools Gold","The Doobie Brothers","Fleetwood Mac"],"category":"Entertainment: Music","difficulty":"medium"},{"id":"otdb_9b24e7e99590","question":"Which of these songs is NOT in The Beatles' album \"Sgt. Pepper's Lonely Hearts Club Band\"?","correct_answer":"Strawberry Fields Forever","incorrect_answers":["Getting Better","Fixing a Hole","Lucy in the Sky with Diamonds"],"category":"Entertainment: Music","difficulty":"medium"},{"id":"otdb_5d6fef08ebc2","question":"Who is the lead singer of Silverchair?","correct_answer":"Daniel Johns","incorrect_answers":["Ben Gillies","Chris Joannou","George Costanza"],"category":"Entertainment: Music","difficulty":"medium"},{"id":"otdb_90a3a274564d","question":"In 2006, which band released their debut album \"A Fever You Can't Sweat Out\"?","correct_answer":"Panic! At the Disco","incorrect_answers":["Twenty One Pilots","My Chemical Romance","Fall Out Boy"],"category":"Entertainment: Music","difficulty":"easy"}]